{".class": "MypyFile", "_fullname": "ecommerce.product.models", "future_import_flags": [], "is_partial_stub_package": false, "is_stub": false, "names": {".class": "SymbolTable", "Brand": {".class": "SymbolTableNode", "kind": "Gdef", "node": {".class": "TypeInfo", "_promote": [], "abstract_attributes": [], "bases": ["builtins.object"], "declared_metaclass": null, "defn": {".class": "ClassDef", "fullname": "ecommerce.product.models.Brand", "name": "Brand", "type_vars": []}, "deletable_attributes": [], "flags": ["fallback_to_any"], "fullname": "ecommerce.product.models.Brand", "has_param_spec_type": false, "metaclass_type": null, "metadata": {}, "module_name": "ecommerce.product.models", "mro": ["ecommerce.product.models.Brand", "builtins.object"], "names": {".class": "SymbolTable", "__str__": {".class": "SymbolTableNode", "kind": "Mdef", "node": {".class": "FuncDef", "abstract_status": 0, "arg_kinds": [0], "arg_names": [null], "flags": [], "fullname": "ecommerce.product.models.Brand.__str__", "name": "__str__", "type": null}}, "name": {".class": "SymbolTableNode", "kind": "Mdef", "node": {".class": "Var", "flags": ["is_initialized_in_class", "is_inferred", "has_explicit_value"], "fullname": "ecommerce.product.models.Brand.name", "name": "name", "type": {".class": "AnyType", "missing_import_name": "ecommerce.product.models.models", "source_any": {".class": "AnyType", "missing_import_name": "ecommerce.product.models.models", "source_any": null, "type_of_any": 3}, "type_of_any": 7}}}}, "self_type": null, "slots": null, "tuple_type": null, "type_vars": [], "typeddict_type": null}}, "Category": {".class": "SymbolTableNode", "kind": "Gdef", "node": {".class": "TypeInfo", "_promote": [], "abstract_attributes": [], "bases": ["builtins.object"], "declared_metaclass": null, "defn": {".class": "ClassDef", "fullname": "ecommerce.product.models.Category", "name": "Category", "type_vars": []}, "deletable_attributes": [], "flags": ["fallback_to_any"], "fullname": "ecommerce.product.models.Category", "has_param_spec_type": false, "metaclass_type": null, "metadata": {}, "module_name": "ecommerce.product.models", "mro": ["ecommerce.product.models.Category", "builtins.object"], "names": {".class": "SymbolTable", "MPTTMeta": {".class": "SymbolTableNode", "kind": "Mdef", "node": {".class": "TypeInfo", "_promote": [], "abstract_attributes": [], "bases": ["builtins.object"], "declared_metaclass": null, "defn": {".class": "ClassDef", "fullname": "ecommerce.product.models.Category.MPTTMeta", "name": "MPTTMeta", "type_vars": []}, "deletable_attributes": [], "flags": [], "fullname": "ecommerce.product.models.Category.MPTTMeta", "has_param_spec_type": false, "metaclass_type": null, "metadata": {}, "module_name": "ecommerce.product.models", "mro": ["ecommerce.product.models.Category.MPTTMeta", "builtins.object"], "names": {".class": "SymbolTable", "order_insertion_by": {".class": "SymbolTableNode", "kind": "Mdef", "node": {".class": "Var", "flags": ["is_initialized_in_class", "is_inferred", "has_explicit_value"], "fullname": "ecommerce.product.models.Category.MPTTMeta.order_insertion_by", "name": "order_insertion_by", "type": {".class": "Instance", "args": ["builtins.str"], "type_ref": "builtins.list"}}}}, "self_type": null, "slots": null, "tuple_type": null, "type_vars": [], "typeddict_type": null}}, "__str__": {".class": "SymbolTableNode", "kind": "Mdef", "node": {".class": "FuncDef", "abstract_status": 0, "arg_kinds": [0], "arg_names": [null], "flags": [], "fullname": "ecommerce.product.models.Category.__str__", "name": "__str__", "type": null}}, "name": {".class": "SymbolTableNode", "kind": "Mdef", "node": {".class": "Var", "flags": ["is_initialized_in_class", "is_inferred", "has_explicit_value"], "fullname": "ecommerce.product.models.Category.name", "name": "name", "type": {".class": "AnyType", "missing_import_name": "ecommerce.product.models.models", "source_any": {".class": "AnyType", "missing_import_name": "ecommerce.product.models.models", "source_any": null, "type_of_any": 3}, "type_of_any": 7}}}, "parent": {".class": "SymbolTableNode", "kind": "Mdef", "node": {".class": "Var", "flags": ["is_initialized_in_class", "is_inferred", "has_explicit_value"], "fullname": "ecommerce.product.models.Category.parent", "name": "parent", "type": {".class": "AnyType", "missing_import_name": "ecommerce.product.models.TreeForeignKey", "source_any": {".class": "AnyType", "missing_import_name": "ecommerce.product.models.TreeForeignKey", "source_any": null, "type_of_any": 3}, "type_of_any": 7}}}}, "self_type": null, "slots": null, "tuple_type": null, "type_vars": [], "typeddict_type": null}}, "MPTTModel": {".class": "SymbolTableNode", "kind": "Gdef", "node": {".class": "Var", "flags": ["is_suppressed_import", "is_ready", "is_inferred"], "fullname": "ecommerce.product.models.MPTTModel", "name": "MPTTModel", "type": {".class": "AnyType", "missing_import_name": "ecommerce.product.models.MPTTModel", "source_any": null, "type_of_any": 3}}}, "Product": {".class": "SymbolTableNode", "kind": "Gdef", "node": {".class": "TypeInfo", "_promote": [], "abstract_attributes": [], "bases": ["builtins.object"], "declared_metaclass": null, "defn": {".class": "ClassDef", "fullname": "ecommerce.product.models.Product", "name": "Product", "type_vars": []}, "deletable_attributes": [], "flags": ["fallback_to_any"], "fullname": "ecommerce.product.models.Product", "has_param_spec_type": false, "metaclass_type": null, "metadata": {}, "module_name": "ecommerce.product.models", "mro": ["ecommerce.product.models.Product", "builtins.object"], "names": {".class": "SymbolTable", "__str__": {".class": "SymbolTableNode", "kind": "Mdef", "node": {".class": "FuncDef", "abstract_status": 0, "arg_kinds": [0], "arg_names": [null], "flags": [], "fullname": "ecommerce.product.models.Product.__str__", "name": "__str__", "type": null}}, "brand": {".class": "SymbolTableNode", "kind": "Mdef", "node": {".class": "Var", "flags": ["is_initialized_in_class", "is_inferred", "has_explicit_value"], "fullname": "ecommerce.product.models.Product.brand", "name": "brand", "type": {".class": "AnyType", "missing_import_name": "ecommerce.product.models.models", "source_any": {".class": "AnyType", "missing_import_name": "ecommerce.product.models.models", "source_any": null, "type_of_any": 3}, "type_of_any": 7}}}, "category": {".class": "SymbolTableNode", "kind": "Mdef", "node": {".class": "Var", "flags": ["is_initialized_in_class", "is_inferred", "has_explicit_value"], "fullname": "ecommerce.product.models.Product.category", "name": "category", "type": {".class": "AnyType", "missing_import_name": "ecommerce.product.models.TreeForeignKey", "source_any": {".class": "AnyType", "missing_import_name": "ecommerce.product.models.TreeForeignKey", "source_any": null, "type_of_any": 3}, "type_of_any": 7}}}, "description": {".class": "SymbolTableNode", "kind": "Mdef", "node": {".class": "Var", "flags": ["is_initialized_in_class", "is_inferred", "has_explicit_value"], "fullname": "ecommerce.product.models.Product.description", "name": "description", "type": {".class": "AnyType", "missing_import_name": "ecommerce.product.models.models", "source_any": {".class": "AnyType", "missing_import_name": "ecommerce.product.models.models", "source_any": null, "type_of_any": 3}, "type_of_any": 7}}}, "is_active": {".class": "SymbolTableNode", "kind": "Mdef", "node": {".class": "Var", "flags": ["is_initialized_in_class", "is_inferred", "has_explicit_value"], "fullname": "ecommerce.product.models.Product.is_active", "name": "is_active", "type": {".class": "AnyType", "missing_import_name": "ecommerce.product.models.models", "source_any": {".class": "AnyType", "missing_import_name": "ecommerce.product.models.models", "source_any": null, "type_of_any": 3}, "type_of_any": 7}}}, "is_digital": {".class": "SymbolTableNode", "kind": "Mdef", "node": {".class": "Var", "flags": ["is_initialized_in_class", "is_inferred", "has_explicit_value"], "fullname": "ecommerce.product.models.Product.is_digital", "name": "is_digital", "type": {".class": "AnyType", "missing_import_name": "ecommerce.product.models.models", "source_any": {".class": "AnyType", "missing_import_name": "ecommerce.product.models.models", "source_any": null, "type_of_any": 3}, "type_of_any": 7}}}, "name": {".class": "SymbolTableNode", "kind": "Mdef", "node": {".class": "Var", "flags": ["is_initialized_in_class", "is_inferred", "has_explicit_value"], "fullname": "ecommerce.product.models.Product.name", "name": "name", "type": {".class": "AnyType", "missing_import_name": "ecommerce.product.models.models", "source_any": {".class": "AnyType", "missing_import_name": "ecommerce.product.models.models", "source_any": null, "type_of_any": 3}, "type_of_any": 7}}}}, "self_type": null, "slots": null, "tuple_type": null, "type_vars": [], "typeddict_type": null}}, "ProductLine": {".class": "SymbolTableNode", "kind": "Gdef", "node": {".class": "TypeInfo", "_promote": [], "abstract_attributes": [], "bases": ["builtins.object"], "declared_metaclass": null, "defn": {".class": "ClassDef", "fullname": "ecommerce.product.models.ProductLine", "name": "ProductLine", "type_vars": []}, "deletable_attributes": [], "flags": ["fallback_to_any"], "fullname": "ecommerce.product.models.ProductLine", "has_param_spec_type": false, "metaclass_type": null, "metadata": {}, "module_name": "ecommerce.product.models", "mro": ["ecommerce.product.models.ProductLine", "builtins.object"], "names": {".class": "SymbolTable", "is_active": {".class": "SymbolTableNode", "kind": "Mdef", "node": {".class": "Var", "flags": ["is_initialized_in_class", "is_inferred", "has_explicit_value"], "fullname": "ecommerce.product.models.ProductLine.is_active", "name": "is_active", "type": {".class": "AnyType", "missing_import_name": "ecommerce.product.models.models", "source_any": {".class": "AnyType", "missing_import_name": "ecommerce.product.models.models", "source_any": null, "type_of_any": 3}, "type_of_any": 7}}}, "price": {".class": "SymbolTableNode", "kind": "Mdef", "node": {".class": "Var", "flags": ["is_initialized_in_class", "is_inferred", "has_explicit_value"], "fullname": "ecommerce.product.models.ProductLine.price", "name": "price", "type": {".class": "AnyType", "missing_import_name": "ecommerce.product.models.models", "source_any": {".class": "AnyType", "missing_import_name": "ecommerce.product.models.models", "source_any": null, "type_of_any": 3}, "type_of_any": 7}}}, "product": {".class": "SymbolTableNode", "kind": "Mdef", "node": {".class": "Var", "flags": ["is_initialized_in_class", "is_inferred", "has_explicit_value"], "fullname": "ecommerce.product.models.ProductLine.product", "name": "product", "type": {".class": "AnyType", "missing_import_name": "ecommerce.product.models.models", "source_any": {".class": "AnyType", "missing_import_name": "ecommerce.product.models.models", "source_any": null, "type_of_any": 3}, "type_of_any": 7}}}, "sku": {".class": "SymbolTableNode", "kind": "Mdef", "node": {".class": "Var", "flags": ["is_initialized_in_class", "is_inferred", "has_explicit_value"], "fullname": "ecommerce.product.models.ProductLine.sku", "name": "sku", "type": {".class": "AnyType", "missing_import_name": "ecommerce.product.models.models", "source_any": {".class": "AnyType", "missing_import_name": "ecommerce.product.models.models", "source_any": null, "type_of_any": 3}, "type_of_any": 7}}}, "stock_qty": {".class": "SymbolTableNode", "kind": "Mdef", "node": {".class": "Var", "flags": ["is_initialized_in_class", "is_inferred", "has_explicit_value"], "fullname": "ecommerce.product.models.ProductLine.stock_qty", "name": "stock_qty", "type": {".class": "AnyType", "missing_import_name": "ecommerce.product.models.models", "source_any": {".class": "AnyType", "missing_import_name": "ecommerce.product.models.models", "source_any": null, "type_of_any": 3}, "type_of_any": 7}}}}, "self_type": null, "slots": null, "tuple_type": null, "type_vars": [], "typeddict_type": null}}, "TreeForeignKey": {".class": "SymbolTableNode", "kind": "Gdef", "node": {".class": "Var", "flags": ["is_suppressed_import", "is_ready", "is_inferred"], "fullname": "ecommerce.product.models.TreeForeignKey", "name": "TreeForeignKey", "type": {".class": "AnyType", "missing_import_name": "ecommerce.product.models.TreeForeignKey", "source_any": null, "type_of_any": 3}}}, "__annotations__": {".class": "SymbolTableNode", "kind": "Gdef", "node": {".class": "Var", "flags": ["is_ready"], "fullname": "ecommerce.product.models.__annotations__", "name": "__annotations__", "type": {".class": "Instance", "args": ["builtins.str", {".class": "AnyType", "missing_import_name": null, "source_any": null, "type_of_any": 6}], "type_ref": "builtins.dict"}}}, "__doc__": {".class": "SymbolTableNode", "kind": "Gdef", "node": {".class": "Var", "flags": ["is_ready"], "fullname": "ecommerce.product.models.__doc__", "name": "__doc__", "type": "builtins.str"}}, "__file__": {".class": "SymbolTableNode", "kind": "Gdef", "node": {".class": "Var", "flags": ["is_ready"], "fullname": "ecommerce.product.models.__file__", "name": "__file__", "type": "builtins.str"}}, "__name__": {".class": "SymbolTableNode", "kind": "Gdef", "node": {".class": "Var", "flags": ["is_ready"], "fullname": "ecommerce.product.models.__name__", "name": "__name__", "type": "builtins.str"}}, "__package__": {".class": "SymbolTableNode", "kind": "Gdef", "node": {".class": "Var", "flags": ["is_ready"], "fullname": "ecommerce.product.models.__package__", "name": "__package__", "type": "builtins.str"}}, "models": {".class": "SymbolTableNode", "kind": "Gdef", "node": {".class": "Var", "flags": ["is_suppressed_import", "is_ready", "is_inferred"], "fullname": "ecommerce.product.models.models", "name": "models", "type": {".class": "AnyType", "missing_import_name": "ecommerce.product.models.models", "source_any": null, "type_of_any": 3}}}}, "path": "c:\\Users\\Desenvolvedor\\Desktop\\e-commerce\\ecommerce\\ecommerce\\product\\models.py"}