{"data_mtime": 1676570600, "dep_lines": [21, 18, 21, 1, 1, 1, 1, 16, 17, 19], "dep_prios": [10, 5, 20, 5, 30, 30, 30, 5, 5, 5], "dependencies": ["ecommerce.product.views", "drf_spectacular.views", "ecommerce.product", "builtins", "abc", "drf_spectacular", "typing"], "hash": "e4dd1a8f90f49b9596272f645a9a9cc5bb5b79b817379291a994d2053abb512d", "id": "ecommerce.urls", "ignore_all": false, "interface_hash": "1bb6a056fd13f77b9f227d5f7a34e0891b795aed3b3df10ab66d3cd6007bc40b", "mtime": 1676570604, "options": {"allow_redefinition": false, "allow_untyped_globals": false, "always_false": [], "always_true": [], "bazel": false, "check_untyped_defs": false, "disable_bytearray_promotion": false, "disable_error_code": [], "disable_memoryview_promotion": false, "disabled_error_codes": [], "disallow_any_decorated": false, "disallow_any_explicit": false, "disallow_any_expr": false, "disallow_any_generics": false, "disallow_any_unimported": false, "disallow_incomplete_defs": false, "disallow_subclassing_any": false, "disallow_untyped_calls": false, "disallow_untyped_decorators": false, "disallow_untyped_defs": false, "enable_error_code": [], "enabled_error_codes": [], "follow_imports": "silent", "follow_imports_for_stubs": false, "ignore_errors": false, "ignore_missing_imports": true, "implicit_optional": false, "implicit_reexport": true, "local_partial_types": false, "mypyc": false, "platform": "win32", "plugins": [], "strict_concatenate": false, "strict_equality": false, "strict_optional": true, "warn_no_return": true, "warn_return_any": false, "warn_unreachable": false, "warn_unused_ignores": false}, "path": "c:\\Users\\Desenvolvedor\\Desktop\\e-commerce\\ecommerce\\ecommerce\\urls.py", "plugin_data": null, "size": 1321, "suppressed": ["django.contrib", "django.urls", "rest_framework.routers"], "version_id": "1.0.0"}